synapse_p2p/__init__.py
synapse_p2p/background.py
synapse_p2p/exceptions.py
synapse_p2p/messages.py
synapse_p2p/serializers.py
synapse_p2p/server.py
synapse_p2p/tests/__init__.py
synapse_p2p/tests/conftest.py
synapse_p2p/tests/test_endpoints.py
synapse_p2p/tests/test_messages.py
synapse_p2p/tests/test_server.py
synapse_p2p/types.py
synapse_p2p/utils.py
synapse_p2p-0.1.4.dist-info/WHEEL
synapse_p2p-0.1.4.dist-info/METADATA
synapse_p2p-0.1.4.dist-info/RECORD
