Metadata-Version: 2.1
Name: synapse-p2p
Version: 0.1.4
Summary: A rapid RPC framework for building p2p networks
Home-page: https://github.com/dvf/synapse
License: UNKNOWN
Author: Daniel van Flymen
Author-email: vanflymen@gmail.com
Requires-Python: >=3.7,<4.0
Classifier: Programming Language :: Python :: 3
Classifier: Programming Language :: Python :: 3.7
Requires-Dist: loguru
Requires-Dist: msgpack
